{
  "_class": "group",
  "do_objectID": "29D12A43-7A14-4001-9C7E-599A41812472",
  "exportOptions": {
    "_class": "exportOptions",
    "exportFormats": [
    ],
    "includedLayerIds": [
    ],
    "layerOptions": 0,
    "shouldTrim": false
  },
  "frame": {
    "_class": "rect",
    "constrainProportions": false,
    "height": 66,
    "width": 113,
    "x": 169,
    "y": 96
  },
  "hasClickThrough": false,
  "isFlippedHorizontal": false,
  "isFlippedVertical": false,
  "isLocked": false,
  "isVisible": true,
  "layerListExpandedType": 0,
  "layers": [
    {
      "class": "text",
      "id": "1B1A109F-B2E0-46BA-AF64-3218A22854FF"
    },
    {
      "class": "text",
      "id": "07774C64-3EC3-4138-9AF5-3473E9503345"
    },
    {
      "class": "text",
      "id": "F47BD488-4F5E-48E5-AF48-E2A991325EED"
    }
  ],
  "name": "Group",
  "nameIsFixed": false,
  "resizingConstraint": 63,
  "resizingType": 0,
  "rotation": 0,
  "shouldBreakMaskChain": false,
  "style": {
    "_class": "style",
    "endDecorationType": 0,
    "miterLimit": 10,
    "startDecorationType": 0
  },
  "userInfo": {
    "com.animaapp.stc-sketch-plugin": {
      "kModelPropertiesKey": {
      }
    }
  }
}