{
  "_class": "group",
  "do_objectID": "958CD0DC-B87E-4D91-A69A-288C3073C35B",
  "exportOptions": {
    "_class": "exportOptions",
    "exportFormats": [
    ],
    "includedLayerIds": [
    ],
    "layerOptions": 0,
    "shouldTrim": false
  },
  "frame": {
    "_class": "rect",
    "constrainProportions": false,
    "height": 181,
    "width": 375,
    "x": 0,
    "y": -1
  },
  "hasClickThrough": false,
  "isFlippedHorizontal": false,
  "isFlippedVertical": false,
  "isLocked": false,
  "isVisible": true,
  "layerListExpandedType": 0,
  "layers": [
    {
      "class": "shapeGroup",
      "id": "67E4D02C-8071-4F38-961B-CE2F5881B2F7"
    },
    {
      "class": "shapeGroup",
      "id": "288D55ED-CB80-4DF6-B11E-D9762B2099DF"
    },
    {
      "class": "text",
      "id": "7B3DAB69-9578-4184-9E85-4E4734657F6D"
    },
    {
      "class": "shapeGroup",
      "id": "C71A4C51-9534-4EEC-9A45-0DF5656EB36E"
    },
    {
      "class": "group",
      "id": "36CE6E9C-D74B-40A4-9C95-DB59C695043C"
    },
    {
      "class": "symbolInstance",
      "id": "738E6CB9-C1EF-4722-B0B9-DADBB4A42AF1"
    },
    {
      "class": "group",
      "id": "B36388C8-CF96-4179-A6EF-5773A7ADE2E4"
    }
  ],
  "name": "Group",
  "nameIsFixed": false,
  "resizingConstraint": 63,
  "resizingType": 0,
  "rotation": 0,
  "shouldBreakMaskChain": false,
  "style": {
    "_class": "style",
    "endDecorationType": 0,
    "miterLimit": 10,
    "startDecorationType": 0
  }
}