{
  "_class": "shapeGroup",
  "clippingMaskMode": 0,
  "do_objectID": "750E31D0-A16C-4E2E-832F-A9758E9A4FAB",
  "exportOptions": {
    "_class": "exportOptions",
    "exportFormats": [
    ],
    "includedLayerIds": [
    ],
    "layerOptions": 0,
    "shouldTrim": false
  },
  "frame": {
    "_class": "rect",
    "constrainProportions": true,
    "height": 237,
    "width": 237,
    "x": 46,
    "y": 141
  },
  "hasClickThrough": false,
  "hasClippingMask": false,
  "isFlippedHorizontal": false,
  "isFlippedVertical": true,
  "isLocked": false,
  "isVisible": true,
  "layerListExpandedType": 0,
  "layers": [
    {
      "class": "oval",
      "id": "1AE5BE5F-E0FB-42AF-B067-0B7819FA913B"
    }
  ],
  "name": "Oval 3",
  "nameIsFixed": false,
  "resizingConstraint": 63,
  "resizingType": 0,
  "rotation": 0,
  "shouldBreakMaskChain": false,
  "style": {
    "_class": "style",
    "borderOptions": {
      "_class": "borderOptions",
      "dashPattern": [
        220,
        1318000
      ],
      "isEnabled": false,
      "lineCapStyle": 0,
      "lineJoinStyle": 0
    },
    "borders": [
      {
        "_class": "border",
        "color": {
          "_class": "color",
          "alpha": 1,
          "blue": 0.8862745098039215,
          "green": 0.8862745098039215,
          "red": 0.8862745098039215
        },
        "fillType": 0,
        "isEnabled": true,
        "position": 0,
        "thickness": 16
      }
    ],
    "endDecorationType": 0,
    "fills": [
      {
        "_class": "fill",
        "color": {
          "_class": "color",
          "alpha": 1,
          "blue": 0.6313725490196078,
          "green": 0.6313725490196078,
          "red": 0.6313725490196078
        },
        "fillType": 0,
        "isEnabled": false,
        "noiseIndex": 0,
        "noiseIntensity": 0,
        "patternFillType": 1,
        "patternTileScale": 1
      }
    ],
    "miterLimit": 10,
    "startDecorationType": 0
  },
  "windingRule": 1
}