{
  "_class": "group",
  "do_objectID": "EA185137-4CEC-469B-AD33-34C953A3D366",
  "exportOptions": {
    "_class": "exportOptions",
    "exportFormats": [
    ],
    "includedLayerIds": [
    ],
    "layerOptions": 0,
    "shouldTrim": false
  },
  "frame": {
    "_class": "rect",
    "constrainProportions": false,
    "height": 61,
    "width": 61,
    "x": 32,
    "y": 10
  },
  "hasClickThrough": false,
  "isFlippedHorizontal": false,
  "isFlippedVertical": false,
  "isLocked": false,
  "isVisible": true,
  "layerListExpandedType": 0,
  "layers": [
    {
      "class": "group",
      "id": "AC0E87D3-7239-42D2-BB69-D71DA0847B7E"
    },
    {
      "class": "group",
      "id": "83C2D90C-A534-4386-9F7C-23C01CB6A8AC"
    }
  ],
  "name": "content",
  "nameIsFixed": true,
  "originalObjectID": "6D9FD98B-6EE1-45FD-B713-E23676C7F432",
  "resizingConstraint": 63,
  "resizingType": 0,
  "rotation": 0,
  "shouldBreakMaskChain": false,
  "style": {
    "_class": "style",
    "endDecorationType": 0,
    "miterLimit": 10,
    "startDecorationType": 0
  }
}