{
  "_class": "group",
  "do_objectID": "CFA88177-EF25-407E-894A-7B2AC2B0423A",
  "exportOptions": {
    "_class": "exportOptions",
    "exportFormats": [
    ],
    "includedLayerIds": [
    ],
    "layerOptions": 0,
    "shouldTrim": false
  },
  "frame": {
    "_class": "rect",
    "constrainProportions": false,
    "height": 13,
    "width": 21,
    "x": 10,
    "y": 30
  },
  "hasClickThrough": false,
  "isFlippedHorizontal": false,
  "isFlippedVertical": false,
  "isLocked": false,
  "isVisible": true,
  "layerListExpandedType": 0,
  "layers": [
    {
      "class": "shapeGroup",
      "id": "5CFF7C38-1A12-48D5-87B8-D46C2306D4F8"
    },
    {
      "class": "shapeGroup",
      "id": "06B83E4E-A997-4195-8E50-2E72C92824DE"
    }
  ],
  "name": "Page 1",
  "nameIsFixed": false,
  "resizingConstraint": 63,
  "resizingType": 0,
  "rotation": 0,
  "shouldBreakMaskChain": false,
  "style": {
    "_class": "style",
    "endDecorationType": 0,
    "miterLimit": 10,
    "startDecorationType": 0
  },
  "userInfo": {
    "com.animaapp.stc-sketch-plugin": {
      "kModelPropertiesKey": {
      }
    }
  }
}