{
  "_class": "group",
  "do_objectID": "979B58CE-D595-44AD-A54C-13A0653C1166",
  "exportOptions": {
    "_class": "exportOptions",
    "exportFormats": [
    ],
    "includedLayerIds": [
    ],
    "layerOptions": 0,
    "shouldTrim": false
  },
  "frame": {
    "_class": "rect",
    "constrainProportions": false,
    "height": 102.0000000000001,
    "width": 375,
    "x": 0,
    "y": 0
  },
  "hasClickThrough": false,
  "isFlippedHorizontal": false,
  "isFlippedVertical": false,
  "isLocked": false,
  "isVisible": true,
  "layerListExpandedType": 0,
  "layers": [
    {
      "class": "shapeGroup",
      "id": "C8654504-2154-4B1F-AF15-A6E4C715ADAE"
    },
    {
      "class": "shapeGroup",
      "id": "376E8FA8-C22B-4F3F-A4F0-620F954BE629"
    },
    {
      "class": "shapeGroup",
      "id": "7BB678EF-09D8-46D2-9F43-72C12BDBB553"
    }
  ],
  "name": "Row",
  "nameIsFixed": true,
  "resizingConstraint": 63,
  "resizingType": 0,
  "rotation": 0,
  "shouldBreakMaskChain": false,
  "style": {
    "_class": "style",
    "endDecorationType": 0,
    "miterLimit": 10,
    "startDecorationType": 0
  },
  "userInfo": {
    "com.animaapp.stc-sketch-plugin": {
      "kModelPropertiesKey": {
      }
    }
  }
}