{
  "_class": "group",
  "do_objectID": "B1AAFD9C-E34A-4B54-896E-B2893C66A5F5",
  "exportOptions": {
    "_class": "exportOptions",
    "exportFormats": [
    ],
    "includedLayerIds": [
    ],
    "layerOptions": 0,
    "shouldTrim": false
  },
  "frame": {
    "_class": "rect",
    "constrainProportions": false,
    "height": 24,
    "width": 77,
    "x": 15,
    "y": 0
  },
  "hasClickThrough": false,
  "isFlippedHorizontal": false,
  "isFlippedVertical": false,
  "isLocked": false,
  "isVisible": true,
  "layerListExpandedType": 2,
  "layers": [
    {
      "class": "text",
      "id": "E60DBF8E-4866-4473-9D0D-40F5D00C889B"
    },
    {
      "class": "symbolInstance",
      "id": "0C0129B5-7F79-45AB-B3F0-70D8A1B98B1D"
    }
  ],
  "name": "Pin",
  "nameIsFixed": true,
  "resizingConstraint": 41,
  "resizingType": 1,
  "rotation": 0,
  "shouldBreakMaskChain": false,
  "style": {
    "_class": "style",
    "endDecorationType": 0,
    "miterLimit": 10,
    "startDecorationType": 0
  }
}