{
  "_class": "shapePath",
  "booleanOperation": -1,
  "do_objectID": "3DAFC111-46C9-43C0-9942-F85C1618D849",
  "edited": true,
  "exportOptions": {
    "_class": "exportOptions",
    "exportFormats": [
    ],
    "includedLayerIds": [
    ],
    "layerOptions": 0,
    "shouldTrim": false
  },
  "frame": {
    "_class": "rect",
    "constrainProportions": false,
    "height": 52.00000000000001,
    "width": 60,
    "x": 0,
    "y": 0
  },
  "isFlippedHorizontal": false,
  "isFlippedVertical": false,
  "isLocked": false,
  "isVisible": true,
  "layerListExpandedType": 0,
  "name": "Path",
  "nameIsFixed": false,
  "path": {
    "_class": "path",
    "isClosed": true,
    "pointRadiusBehaviour": 0,
    "points": [
      {
        "_class": "curvePoint",
        "cornerRadius": 0,
        "curveFrom": "{1, 0.096153846153846159}",
        "curveMode": 4,
        "curveTo": "{1, 0.043269230769230768}",
        "hasCurveFrom": false,
        "hasCurveTo": true,
        "point": "{1, 0.096153846153846159}"
      },
      {
        "_class": "curvePoint",
        "cornerRadius": 0,
        "curveFrom": "{1, 0.80288461538461542}",
        "curveMode": 4,
        "curveTo": "{1, 0.75}",
        "hasCurveFrom": true,
        "hasCurveTo": false,
        "point": "{1, 0.75}"
      },
      {
        "_class": "curvePoint",
        "cornerRadius": 0,
        "curveFrom": "{0.91666666666666663, 0.84615384615384615}",
        "curveMode": 4,
        "curveTo": "{0.96250000000000002, 0.84615384615384615}",
        "hasCurveFrom": false,
        "hasCurveTo": true,
        "point": "{0.91666666666666663, 0.84615384615384615}"
      },
      {
        "_class": "curvePoint",
        "cornerRadius": 0,
        "curveFrom": "{0.6333333333333333, 0.89723076923076917}",
        "curveMode": 4,
        "curveTo": "{0.6333333333333333, 0.84615384615384615}",
        "hasCurveFrom": true,
        "hasCurveTo": false,
        "point": "{0.6333333333333333, 0.84615384615384615}"
      },
      {
        "_class": "curvePoint",
        "cornerRadius": 0,
        "curveFrom": "{0.66666666666666663, 0.98257692307692313}",
        "curveMode": 2,
        "curveTo": "{0.66666666666666663, 0.9405}",
        "hasCurveFrom": true,
        "hasCurveTo": true,
        "point": "{0.66666666666666663, 0.96153846153846156}"
      },
      {
        "_class": "curvePoint",
        "cornerRadius": 0,
        "curveFrom": "{0.6333333333333333, 1}",
        "curveMode": 4,
        "curveTo": "{0.65156666666666674, 1}",
        "hasCurveFrom": false,
        "hasCurveTo": true,
        "point": "{0.6333333333333333, 1}"
      },
      {
        "_class": "curvePoint",
        "cornerRadius": 0,
        "curveFrom": "{0.34843333333333332, 1}",
        "curveMode": 4,
        "curveTo": "{0.36666666666666664, 1}",
        "hasCurveFrom": true,
        "hasCurveTo": false,
        "point": "{0.36666666666666664, 1}"
      },
      {
        "_class": "curvePoint",
        "cornerRadius": 0,
        "curveFrom": "{0.33333333333333331, 0.93930769230769229}",
        "curveMode": 2,
        "curveTo": "{0.33333333333333331, 0.98257692307692313}",
        "hasCurveFrom": true,
        "hasCurveTo": true,
        "point": "{0.33333333333333331, 0.96153846153846156}"
      },
      {
        "_class": "curvePoint",
        "cornerRadius": 0,
        "curveFrom": "{0.36666666666666664, 0.84615384615384615}",
        "curveMode": 4,
        "curveTo": "{0.36666666666666664, 0.89842307692307699}",
        "hasCurveFrom": false,
        "hasCurveTo": true,
        "point": "{0.36666666666666664, 0.84615384615384615}"
      },
      {
        "_class": "curvePoint",
        "cornerRadius": 0,
        "curveFrom": "{0.037499999999999999, 0.84615384615384615}",
        "curveMode": 4,
        "curveTo": "{0.083333333333333329, 0.84615384615384615}",
        "hasCurveFrom": true,
        "hasCurveTo": false,
        "point": "{0.083333333333333329, 0.84615384615384615}"
      },
      {
        "_class": "curvePoint",
        "cornerRadius": 0,
        "curveFrom": "{0, 0.75}",
        "curveMode": 4,
        "curveTo": "{0, 0.80288461538461542}",
        "hasCurveFrom": false,
        "hasCurveTo": true,
        "point": "{0, 0.75}"
      },
      {
        "_class": "curvePoint",
        "cornerRadius": 0,
        "curveFrom": "{0, 0.043269230769230768}",
        "curveMode": 4,
        "curveTo": "{0, 0.096153846153846159}",
        "hasCurveFrom": true,
        "hasCurveTo": false,
        "point": "{0, 0.096153846153846159}"
      },
      {
        "_class": "curvePoint",
        "cornerRadius": 0,
        "curveFrom": "{0.083333333333333329, 0}",
        "curveMode": 4,
        "curveTo": "{0.037499999999999999, 0}",
        "hasCurveFrom": false,
        "hasCurveTo": true,
        "point": "{0.083333333333333329, 0}"
      },
      {
        "_class": "curvePoint",
        "cornerRadius": 0,
        "curveFrom": "{0.96250000000000002, 0}",
        "curveMode": 4,
        "curveTo": "{0.91666666666666663, 0}",
        "hasCurveFrom": true,
        "hasCurveTo": false,
        "point": "{0.91666666666666663, 0}"
      }
    ]
  },
  "resizingConstraint": 63,
  "resizingType": 0,
  "rotation": 0,
  "shouldBreakMaskChain": false
}