{
  "_class": "artboard",
  "backgroundColor": {
    "_class": "color",
    "alpha": 1,
    "blue": 0.9529411764705882,
    "green": 0.9529411764705882,
    "red": 0.9529411764705882
  },
  "do_objectID": "978C6D47-BA3A-4540-B26B-2879497D8B55",
  "exportOptions": {
    "_class": "exportOptions",
    "exportFormats": [
      {
        "_class": "exportFormat",
        "absoluteSize": 0,
        "fileFormat": "png",
        "name": "",
        "namingScheme": 0,
        "scale": 2,
        "visibleScaleType": 0
      }
    ],
    "includedLayerIds": [
    ],
    "layerOptions": 0,
    "shouldTrim": false
  },
  "frame": {
    "_class": "rect",
    "constrainProportions": false,
    "height": 667,
    "width": 375,
    "x": 4045,
    "y": 3233
  },
  "grid": {
    "_class": "simpleGrid",
    "gridSize": 10,
    "isEnabled": false,
    "thickGridTimes": 10
  },
  "hasBackgroundColor": true,
  "hasClickThrough": true,
  "horizontalRulerData": {
    "_class": "rulerData",
    "base": 0,
    "guides": [
      10,
      365
    ]
  },
  "includeBackgroundColorInExport": true,
  "includeInCloudUpload": true,
  "isFlippedHorizontal": false,
  "isFlippedVertical": false,
  "isLocked": false,
  "isVisible": true,
  "layerListExpandedType": 2,
  "layers": [
    {
      "class": "shapeGroup",
      "id": "C0CEF4E1-E801-4EC4-ADD1-DE3D9C5BED8F"
    },
    {
      "class": "text",
      "id": "9498419D-665C-49BD-BB00-404D01F686AF"
    },
    {
      "class": "group",
      "id": "EC15C2E8-BB12-4556-BD6F-BF5553FEECBB"
    },
    {
      "class": "symbolInstance",
      "id": "79A21A7C-2946-4AEA-832E-2BD1C046458F"
    },
    {
      "class": "symbolInstance",
      "id": "CF460A0F-EB6D-401C-926D-406C0A675792"
    },
    {
      "class": "symbolInstance",
      "id": "5441E3FC-2FB3-4C18-8480-D7DD51EDD644"
    }
  ],
  "name": "MyLife - Add Event - 4.1",
  "nameIsFixed": true,
  "resizesContent": false,
  "resizingConstraint": 63,
  "resizingType": 0,
  "rotation": 0,
  "shouldBreakMaskChain": true,
  "style": {
    "_class": "style",
    "endDecorationType": 0,
    "fills": [
      {
        "_class": "fill",
        "color": {
          "_class": "color",
          "alpha": 1,
          "blue": 1,
          "green": 1,
          "red": 1
        },
        "fillType": 0,
        "isEnabled": true,
        "noiseIndex": 0,
        "noiseIntensity": 0,
        "patternFillType": 0,
        "patternTileScale": 1
      }
    ],
    "miterLimit": 10,
    "startDecorationType": 0
  },
  "userInfo": {
    "com.animaapp.stc-sketch-plugin": {
      "kModelPropertiesKey": {
      }
    }
  },
  "verticalRulerData": {
    "_class": "rulerData",
    "base": 0,
    "guides": [
      20,
      64,
      617
    ]
  }
}