{
  "_class": "group",
  "do_objectID": "2A9458F8-A8E2-4014-91CB-723B3851807C",
  "exportOptions": {
    "_class": "exportOptions",
    "exportFormats": [
    ],
    "includedLayerIds": [
    ],
    "layerOptions": 0,
    "shouldTrim": false
  },
  "frame": {
    "_class": "rect",
    "constrainProportions": false,
    "height": 121,
    "width": 375,
    "x": 0,
    "y": 309
  },
  "hasClickThrough": false,
  "isFlippedHorizontal": false,
  "isFlippedVertical": false,
  "isLocked": false,
  "isVisible": true,
  "layerListExpandedType": 0,
  "layers": [
    {
      "class": "shapeGroup",
      "id": "9E6A6697-B10F-457D-92DE-3FE6D0EC4264"
    },
    {
      "class": "group",
      "id": "E19EAD10-DE46-4B88-94FD-92F4CE83BD0B"
    }
  ],
  "name": "Group Copy",
  "nameIsFixed": false,
  "resizingConstraint": 63,
  "resizingType": 0,
  "rotation": 0,
  "shouldBreakMaskChain": false,
  "style": {
    "_class": "style",
    "endDecorationType": 0,
    "miterLimit": 10,
    "startDecorationType": 0
  }
}