{
  "_class": "group",
  "do_objectID": "615C6306-F6A7-444C-BC60-3A22163BBC1D",
  "exportOptions": {
    "_class": "exportOptions",
    "exportFormats": [
    ],
    "includedLayerIds": [
    ],
    "layerOptions": 0,
    "shouldTrim": false
  },
  "frame": {
    "_class": "rect",
    "constrainProportions": false,
    "height": 181,
    "width": 375,
    "x": 0,
    "y": -1
  },
  "hasClickThrough": false,
  "isFlippedHorizontal": false,
  "isFlippedVertical": false,
  "isLocked": false,
  "isVisible": true,
  "layerListExpandedType": 0,
  "layers": [
    {
      "class": "shapeGroup",
      "id": "CC93BF7B-D00F-49BB-AB94-3824436B1436"
    },
    {
      "class": "shapeGroup",
      "id": "5F7E153D-40FD-4189-B10A-8490DC5BF2BA"
    },
    {
      "class": "text",
      "id": "BC99DE3B-45C8-45D1-9BA8-7CC6DD153BAD"
    },
    {
      "class": "shapeGroup",
      "id": "311B40C8-410C-48B9-A4CC-F679EC905EF2"
    },
    {
      "class": "group",
      "id": "EC6A3462-2BEB-40AF-9EA7-61C21EA280FA"
    },
    {
      "class": "symbolInstance",
      "id": "DBD7DB65-821B-440F-B565-A9FD0A94FD51"
    },
    {
      "class": "group",
      "id": "C7B09DC8-11CB-46FB-931C-BAB8741D90AD"
    }
  ],
  "name": "Group",
  "nameIsFixed": false,
  "resizingConstraint": 63,
  "resizingType": 0,
  "rotation": 0,
  "shouldBreakMaskChain": false,
  "style": {
    "_class": "style",
    "endDecorationType": 0,
    "miterLimit": 10,
    "startDecorationType": 0
  }
}