{
  "_class": "group",
  "do_objectID": "D561E05C-C891-40CA-A75B-1584C6F11C2E",
  "exportOptions": {
    "_class": "exportOptions",
    "exportFormats": [
    ],
    "includedLayerIds": [
    ],
    "layerOptions": 0,
    "shouldTrim": false
  },
  "frame": {
    "_class": "rect",
    "constrainProportions": false,
    "height": 18,
    "width": 18,
    "x": 302,
    "y": 20
  },
  "hasClickThrough": false,
  "isFlippedHorizontal": false,
  "isFlippedVertical": false,
  "isLocked": false,
  "isVisible": true,
  "layerListExpandedType": 0,
  "layers": [
    {
      "class": "shapeGroup",
      "id": "DD589034-7314-4E10-BAAB-FEBC78685FB2"
    },
    {
      "class": "group",
      "id": "1AD051AB-7F56-4F2F-8ACC-BA48025C5B4E"
    }
  ],
  "name": "edit",
  "nameIsFixed": true,
  "originalObjectID": "4E79CC6C-8483-4578-A7C0-F602EEAED1FD",
  "resizingConstraint": 63,
  "resizingType": 0,
  "rotation": 0,
  "shouldBreakMaskChain": false,
  "style": {
    "_class": "style",
    "endDecorationType": 0,
    "miterLimit": 10,
    "startDecorationType": 0
  }
}