{
  "_class": "group",
  "do_objectID": "9D87A5A6-5BAF-4400-B87D-D828162A4972",
  "exportOptions": {
    "_class": "exportOptions",
    "exportFormats": [
    ],
    "includedLayerIds": [
    ],
    "layerOptions": 0,
    "shouldTrim": false
  },
  "frame": {
    "_class": "rect",
    "constrainProportions": false,
    "height": 14,
    "width": 14,
    "x": 16,
    "y": 110
  },
  "hasClickThrough": false,
  "isFlippedHorizontal": false,
  "isFlippedVertical": false,
  "isLocked": false,
  "isVisible": true,
  "layerListExpandedType": 0,
  "layers": [
    {
      "class": "shapeGroup",
      "id": "662CDFA7-5862-4C4E-A9E7-D06FD31679C5"
    },
    {
      "class": "symbolInstance",
      "id": "E0E2EE04-90EA-4A66-A9B1-1ADCC0E068AB"
    }
  ],
  "name": "check",
  "nameIsFixed": true,
  "resizingConstraint": 63,
  "resizingType": 0,
  "rotation": 0,
  "shouldBreakMaskChain": false,
  "style": {
    "_class": "style",
    "endDecorationType": 0,
    "miterLimit": 10,
    "startDecorationType": 0
  }
}